mcpeureka/__init__.py
mcpeureka/main.py
czyhandsome_eureka_mcp-0.1.4.dist-info/METADATA
czyhandsome_eureka_mcp-0.1.4.dist-info/WHEEL
czyhandsome_eureka_mcp-0.1.4.dist-info/entry_points.txt
czyhandsome_eureka_mcp-0.1.4.dist-info/RECORD
