Metadata-Version: 2.4
Name: czyhandsome-eureka-mcp
Version: 0.1.4
Summary: Eureka MCP - search Spring Cloud Eureka servers for debugging
Author-email: czyhandsome <czyhandsome@foxmail.com>
License: MIT
Keywords: eureka,mcp,protocol,server,spring-cloud
Requires-Python: >=3.12
Requires-Dist: mcp-python>=0.1.4
Requires-Dist: requests>=2.32.3
